msba_one/__init__.py
macrogpt-0.1.1.dist-info/METADATA
macrogpt-0.1.1.dist-info/WHEEL
macrogpt-0.1.1.dist-info/top_level.txt
macrogpt-0.1.1.dist-info/RECORD
